lispium/__init__.py
lispium/cli.py
lispium/bin/lispium-darwin-aarch64
lispium/bin/lispium-darwin-x86_64
lispium/bin/lispium-linux-x86_64
lispium/bin/lispium-windows-x86_64.exe
lispium-0.4.0.dist-info/METADATA
lispium-0.4.0.dist-info/WHEEL
lispium-0.4.0.dist-info/entry_points.txt
lispium-0.4.0.dist-info/top_level.txt
lispium-0.4.0.dist-info/RECORD
