Metadata-Version: 2.4
Name: lispium
Version: 0.4.0
Summary: A Symbolic Computer Algebra System
Author-email: Tetraslam <tetraslam@users.noreply.github.com>
License: MIT
Project-URL: Homepage, https://github.com/Tetraslam/lispium
Project-URL: Repository, https://github.com/Tetraslam/lispium
Project-URL: Issues, https://github.com/Tetraslam/lispium/issues
Keywords: cas,computer-algebra,symbolic-math,lisp,mathematics
Classifier: Development Status :: 4 - Beta
Classifier: Environment :: Console
Classifier: Intended Audience :: Science/Research
Classifier: Intended Audience :: Education
Classifier: License :: OSI Approved :: MIT License
Classifier: Operating System :: OS Independent
Classifier: Programming Language :: Other
Classifier: Topic :: Scientific/Engineering :: Mathematics
Requires-Python: >=3.8
